pyattimo-0.7.1.dist-info/METADATA
pyattimo-0.7.1.dist-info/WHEEL
pyattimo/__init__.py
pyattimo/pyattimo.abi3.so
pyattimo-0.7.1.dist-info/RECORD
