Metadata-Version: 2.4
Name: pyattimo
Version: 0.7.1
Classifier: Programming Language :: Rust
Classifier: Programming Language :: Python :: Implementation :: CPython
Classifier: Programming Language :: Python :: Implementation :: PyPy
Summary: A fast and scalable algorithm for time series motif mining.
Requires-Python: >=3.6
